Wilbur/CLI.py
Wilbur/DataBlob.py
Wilbur/DataMill.py
Wilbur/Scheme.py
Wilbur/YaModules/Alias.py
Wilbur/YaModules/Classifier.py
Wilbur/YaModules/Filter.py
Wilbur/YaModules/__init__.py
Wilbur/__init__.py
wilbur-0.1.0.dist-info/METADATA
wilbur-0.1.0.dist-info/WHEEL
wilbur-0.1.0.dist-info/RECORD
